UART.srcs/sources_1/new/receive.v
module receive(I,clk,O,r_done);
  
  input I,clk;
  
  output reg [7:0] O;
  output reg r_done=0;
  
  parameter S0=2'b00,S1=2'b01,S2=2'b10,S3=2'b11;
    
  reg [1:0] state=S0;
  
  integer cpb=26;
  
  reg [7:0] clk_count=0,i=0;

  always @(posedge clk)
   begin
     case(state)
      S0: begin
        if(I==0) state=S1;
           else state=S0;
           r_done=0;
           end
       
     S1:  begin                           
          if(clk_count<cpb-1)
             begin 
                clk_count<=clk_count+1;
                state=S1;
              end
           else
             begin
              state=S2;
              clk_count=0;
             end
          end 
       
       S2: begin            
            if(clk_count<cpb-1)
              begin
                clk_count<=clk_count+1;
                state=S2;
                O[i]=I;
              end
            else
             begin
              clk_count=0;
              if(i<7)
                begin
                 state=S2;
                 i<=i+1;
                end
               else
                 begin 
                  i=0;
                  state=S3;
                  r_done=1;
                 end
             end
          end 
       
       S3: begin      
           if(I==1)
           begin
              if(clk_count<cpb-1)
               begin 
                clk_count<=clk_count+1;
                state=S3;
               end
             else
               begin
                state=S0;
                clk_count=0;
                cpb<=cpb*2;
               end
           end
         end
      endcase
   end
endmodule

UART.srcs/sources_1/new/transmit.v
module transmit(clk,start,in,stop,t_active,out,t_done);
  
  input clk,start,stop;
  input [7:0] in;
  
  output reg out,t_active=0,t_done=0;

  parameter S0=2'b00,S1=2'b01,S2=2'b10,S3=2'b11;
   
  integer cpb=26; 

  reg [1:0] state=S0; 
  
  reg [7:0] data,clk_count=0,i=0;
  
  always @(posedge clk) 
   begin
    case(state)
      S0 : begin
           out=1;
           t_done=0;
           if(start==0)
              begin
                t_active= 1'b1;
                data<=in;
                state=S1;
              end
            else
            state=S0;
           end
      
      S1 : begin
          out<=0; 
		  if(clk_count<cpb-1)
             begin 
                clk_count<=clk_count+1;
                state=S1;
              end
           else
             begin
              state=S2;
              clk_count=0;
             end
         end
      
      S2 : begin
           out<=data[i];
        if(clk_count<cpb-1)
           begin
            clk_count<=clk_count+1;
            state=S2;
           end
         else
          begin
            clk_count=0;
            if(i<7)
              begin
                state=S2;
                i<=i+1;
              end
            else
             begin i=0;
              state=S3;
             end
           end
       end
        
       S3 : begin
          out<=1; //transmit stop bit
         if(clk_count<cpb-1)
             begin 
                clk_count<=clk_count+1;
                state=S3;
              end
           else
             begin
              state=S0;
              clk_count=0;
              t_done=1;
              cpb<=cpb*2;
             end
         
         end 
      
       endcase
     
      end
              
 endmodule

UART.srcs/sources_1/new/UART_tb.v
module UART_tb;
  reg clk,start,stop;
  reg [7:0] in;
  wire out,t_done,t_active,r_done;
  wire [7:0] O;

  transmit inst(clk,start,in,stop,t_active,out,t_done);
  receive inst1(out,clk,O,r_done);
  
   initial
     repeat(2000)
    #200 clk=~clk;   // baud rate=9600 bps
                      // frequency of our clock input=250 kHz
                      // 250000/9600=26 clock cyles per bit
                     //We have a fixed clk input 
  initial
    begin
      $dumpfile("UART_tb.vcd");
      $dumpvars(0,UART_tb);
      clk=0;
      start=1'b0;
      in=8'b11010001;
      stop=1'b1;
    end
  

  
  initial 
    begin
    $monitor($time,"   t_active=%b    out=%b     t_done=%b",t_active,out,t_done);
      $monitor($time,"   O=%b              r_done=%b",O,r_done);
    end
        
  
endmodule

UART.sim/sim_1/behav/xsim/UART_tb.vcd
$date
   Sun Jun 18 12:31:57 2023
$end
$version
  2018.2
$end
$timescale
  1ps
$end
$scope module UART_tb $end
$var reg 1 ! clk $end
$var reg 1 " start $end
$var reg 1 # stop $end
$var reg 8 $ in [7:0] $end
$var wire 1 % out $end
$var wire 1 & t_done $end
$var wire 1 ' t_active $end
$var wire 1 ( r_done $end
$var wire 8 ) O [7:0] $end
$scope module inst $end
$var wire 1 * clk $end
$var wire 1 + start $end
$var wire 1 , stop $end
$var wire 8 - in [7:0] $end
$var reg 1 . out $end
$var reg 1 / t_active $end
$var reg 1 0 t_done $end
$var integer 32 1 cpb $end
$var reg 2 2 state [1:0] $end
$var reg 8 3 data [7:0] $end
$var reg 8 4 clk_count [7:0] $end
$var reg 8 5 i [7:0] $end
$var parameter 2 6 S0 [1:0] $end
$var parameter 2 7 S1 [1:0] $end
$var parameter 2 8 S2 [1:0] $end
$var parameter 2 9 S3 [1:0] $end
$upscope $end
$scope module inst1 $end
$var wire 1 % I $end
$var wire 1 : clk $end
$var reg 8 ; O [7:0] $end
$var reg 1 < r_done $end
$var reg 2 = state [1:0] $end
$var integer 32 > cpb $end
$var reg 8 ? clk_count [7:0] $end
$var reg 8 @ i [7:0] $end
$var parameter 2 A S0 [1:0] $end
$var parameter 2 B S1 [1:0] $end
$var parameter 2 C S2 [1:0] $end
$var parameter 2 D S3 [1:0] $end
$upscope $end
$upscope $end
$enddefinitions $end
#0
$dumpvars
0!
0"
1#
b11010001 $
x%
0&
0'
0(
bx )
0*
0+
1,
b11010001 -
x.
0/
00
b11010 1
b0 2
bx 3
b0 4
b0 5
b0 6
b1 7
b10 8
b11 9
0:
bx ;
0<
b0 =
b11010 >
b0 ?
b0 @
b0 A
b1 B
b10 C
b11 D
$end
#200000
1!
1%
1'
1*
1.
1/
00
b1 2
b11010001 3
1:
0<
#400000
0!
0*
0:
#600000
1!
0%
1*
0.
b1 4
1:
0<
#800000
0!
0*
0:
#1000000
1!
1*
0.
b10 4
1:
0<
b1 =
#1200000
0!
0*
0:
#1400000
1!
1*
0.
b11 4
1:
b1 ?
#1600000
0!
0*
0:
#1800000
1!
1*
0.
b100 4
1:
b10 ?
#2000000
0!
0*
0:
#2200000
1!
1*
0.
b101 4
1:
b11 ?
#2400000
0!
0*
0:
#2600000
1!
1*
0.
b110 4
1:
b100 ?
#2800000
0!
0*
0:
#3000000
1!
1*
0.
b111 4
1:
b101 ?
#3200000
0!
0*
0:
#3400000
1!
1*
0.
b1000 4
1:
b110 ?
#3600000
0!
0*
0:
#3800000
1!
1*
0.
b1001 4
1:
b111 ?
#4000000
0!
0*
0:
#4200000
1!
1*
0.
b1010 4
1:
b1000 ?
#4400000
0!
0*
0:
#4600000
1!
1*
0.
b1011 4
1:
b1001 ?
#4800000
0!
0*
0:
#5000000
1!
1*
0.
b1100 4
1:
b1010 ?
#5200000
0!
0*
0:
#5400000
1!
1*
0.
b1101 4
1:
b1011 ?
#5600000
0!
0*
0:
#5800000
1!
1*
0.
b1110 4
1:
b1100 ?
#6000000
0!
0*
0:
#6200000
1!
1*
0.
b1111 4
1:
b1101 ?
#6400000
0!
0*
0:
#6600000
1!
1*
0.
b10000 4
1:
b1110 ?
#6800000
0!
0*
0:
#7000000
1!
1*
0.
b10001 4
1:
b1111 ?
#7200000
0!
0*
0:
#7400000
1!
1*
0.
b10010 4
1:
b10000 ?
#7600000
0!
0*
0:
#7800000
1!
1*
0.
b10011 4
1:
b10001 ?
#8000000
0!
0*
0:
#8200000
1!
1*
0.
b10100 4
1:
b10010 ?
#8400000
0!
0*
0:
#8600000
1!
1*
0.
b10101 4
1:
b10011 ?
#8800000
0!
0*
0:
#9000000
1!
1*
0.
b10110 4
1:
b10100 ?
#9200000
0!
0*
0:
#9400000
1!
1*
0.
b10111 4
1:
b10101 ?
#9600000
0!
0*
0:
#9800000
1!
1*
0.
b11000 4
1:
b10110 ?
#10000000
0!
0*
0:
#10200000
1!
1*
0.
b11001 4
1:
b10111 ?
#10400000
0!
0*
0:
#10600000
1!
1*
0.
b10 2
b0 4
1:
b11000 ?
#10800000
0!
0*
0:
#11000000
1!
1%
1*
1.
b1 4
1:
b11001 ?
#11200000
0!
0*
0:
#11400000
1!
1*
1.
b10 4
1:
b10 =
b0 ?
#11600000
0!
0*
0:
#11800000
1!
bx1 )
1*
1.
b11 4
1:
bx1 ;
b1 ?
#12000000
0!
0*
0:
#12200000
1!
1*
1.
b100 4
1:
bx1 ;
b10 ?
#12400000
0!
0*
0:
#12600000
1!
1*
1.
b101 4
1:
bx1 ;
b11 ?
#12800000
0!
0*
0:
#13000000
1!
1*
1.
b110 4
1:
bx1 ;
b100 ?
#13200000
0!
0*
0:
#13400000
1!
1*
1.
b111 4
1:
bx1 ;
b101 ?
#13600000
0!
0*
0:
#13800000
1!
1*
1.
b1000 4
1:
bx1 ;
b110 ?
#14000000
0!
0*
0:
#14200000
1!
1*
1.
b1001 4
1:
bx1 ;
b111 ?
#14400000
0!
0*
0:
#14600000
1!
1*
1.
b1010 4
1:
bx1 ;
b1000 ?
#14800000
0!
0*
0:
#15000000
1!
1*
1.
b1011 4
1:
bx1 ;
b1001 ?
#15200000
0!
0*
0:
#15400000
1!
1*
1.
b1100 4
1:
bx1 ;
b1010 ?
#15600000
0!
0*
0:
#15800000
1!
1*
1.
b1101 4
1:
bx1 ;
b1011 ?
#16000000
0!
0*
0:
#16200000
1!
1*
1.
b1110 4
1:
bx1 ;
b1100 ?
#16400000
0!
0*
0:
#16600000
1!
1*
1.
b1111 4
1:
bx1 ;
b1101 ?
#16800000
0!
0*
0:
#17000000
1!
1*
1.
b10000 4
1:
bx1 ;
b1110 ?
#17200000
0!
0*
0:
#17400000
1!
1*
1.
b10001 4
1:
bx1 ;
b1111 ?
#17600000
0!
0*
0:
#17800000
1!
1*
1.
b10010 4
1:
bx1 ;
b10000 ?
#18000000
0!
0*
0:
#18200000
1!
1*
1.
b10011 4
1:
bx1 ;
b10001 ?
#18400000
0!
0*
0:
#18600000
1!
1*
1.
b10100 4
1:
bx1 ;
b10010 ?
#18800000
0!
0*
0:
#19000000
1!
1*
1.
b10101 4
1:
bx1 ;
b10011 ?
#19200000
0!
0*
0:
#19400000
1!
1*
1.
b10110 4
1:
bx1 ;
b10100 ?
#19600000
0!
0*
0:
#19800000
1!
1*
1.
b10111 4
1:
bx1 ;
b10101 ?
#20000000
0!
0*
0:
#20200000
1!
1*
1.
b11000 4
1:
bx1 ;
b10110 ?
#20400000
0!
0*
0:
#20600000
1!
1*
1.
b11001 4
1:
bx1 ;
b10111 ?
#20800000
0!
0*
0:
#21000000
1!
1*
1.
b0 4
b1 5
1:
bx1 ;
b11000 ?
#21200000
0!
0*
0:
#21400000
1!
0%
1*
0.
b1 4
1:
bx1 ;
b11001 ?
#21600000
0!
0*
0:
#21800000
1!
1*
0.
b10 4
1:
b0 ?
b1 @
#22000000
0!
0*
0:
#22200000
1!
bx01 )
1*
0.
b11 4
1:
bx01 ;
b1 ?
#22400000
0!
0*
0:
#22600000
1!
1*
0.
b100 4
1:
bx01 ;
b10 ?
#22800000
0!
0*
0:
#23000000
1!
1*
0.
b101 4
1:
bx01 ;
b11 ?
#23200000
0!
0*
0:
#23400000
1!
1*
0.
b110 4
1:
bx01 ;
b100 ?
#23600000
0!
0*
0:
#23800000
1!
1*
0.
b111 4
1:
bx01 ;
b101 ?
#24000000
0!
0*
0:
#24200000
1!
1*
0.
b1000 4
1:
bx01 ;
b110 ?
#24400000
0!
0*
0:
#24600000
1!
1*
0.
b1001 4
1:
bx01 ;
b111 ?
#24800000
0!
0*
0:
#25000000
1!
1*
0.
b1010 4
1:
bx01 ;
b1000 ?
#25200000
0!
0*
0:
#25400000
1!
1*
0.
b1011 4
1:
bx01 ;
b1001 ?
#25600000
0!
0*
0:
#25800000
1!
1*
0.
b1100 4
1:
bx01 ;
b1010 ?
#26000000
0!
0*
0:
#26200000
1!
1*
0.
b1101 4
1:
bx01 ;
b1011 ?
#26400000
0!
0*
0:
#26600000
1!
1*
0.
b1110 4
1:
bx01 ;
b1100 ?
#26800000
0!
0*
0:
#27000000
1!
1*
0.
b1111 4
1:
bx01 ;
b1101 ?
#27200000
0!
0*
0:
#27400000
1!
1*
0.
b10000 4
1:
bx01 ;
b1110 ?
#27600000
0!
0*
0:
#27800000
1!
1*
0.
b10001 4
1:
bx01 ;
b1111 ?
#28000000
0!
0*
0:
#28200000
1!
1*
0.
b10010 4
1:
bx01 ;
b10000 ?
#28400000
0!
0*
0:
#28600000
1!
1*
0.
b10011 4
1:
bx01 ;
b10001 ?
#28800000
0!
0*
0:
#29000000
1!
1*
0.
b10100 4
1:
bx01 ;
b10010 ?
#29200000
0!
0*
0:
#29400000
1!
1*
0.
b10101 4
1:
bx01 ;
b10011 ?
#29600000
0!
0*
0:
#29800000
1!
1*
0.
b10110 4
1:
bx01 ;
b10100 ?
#30000000
0!
0*
0:
#30200000
1!
1*
0.
b10111 4
1:
bx01 ;
b10101 ?
#30400000
0!
0*
0:
#30600000
1!
1*
0.
b11000 4
1:
bx01 ;
b10110 ?
#30800000
0!
0*
0:
#31000000
1!
1*
0.
b11001 4
1:
bx01 ;
b10111 ?
#31200000
0!
0*
0:
#31400000
1!
1*
0.
b0 4
b10 5
1:
bx01 ;
b11000 ?
#31600000
0!
0*
0:
#31800000
1!
1*
0.
b1 4
1:
bx01 ;
b11001 ?
#32000000
0!
0*
0:
#32200000
1!
1*
0.
b10 4
1:
b0 ?
b10 @
#32400000
0!
0*
0:
#32600000
1!
bx001 )
1*
0.
b11 4
1:
bx001 ;
b1 ?
#32800000
0!
0*
0:
#33000000
1!
1*
0.
b100 4
1:
bx001 ;
b10 ?
#33200000
0!
0*
0:
#33400000
1!
1*
0.
b101 4
1:
bx001 ;
b11 ?
#33600000
0!
0*
0:
#33800000
1!
1*
0.
b110 4
1:
bx001 ;
b100 ?
#34000000
0!
0*
0:
#34200000
1!
1*
0.
b111 4
1:
bx001 ;
b101 ?
#34400000
0!
0*
0:
#34600000
1!
1*
0.
b1000 4
1:
bx001 ;
b110 ?
#34800000
0!
0*
0:
#35000000
1!
1*
0.
b1001 4
1:
bx001 ;
b111 ?
#35200000
0!
0*
0:
#35400000
1!
1*
0.
b1010 4
1:
bx001 ;
b1000 ?
#35600000
0!
0*
0:
#35800000
1!
1*
0.
b1011 4
1:
bx001 ;
b1001 ?
#36000000
0!
0*
0:
#36200000
1!
1*
0.
b1100 4
1:
bx001 ;
b1010 ?
#36400000
0!
0*
0:
#36600000
1!
1*
0.
b1101 4
1:
bx001 ;
b1011 ?
#36800000
0!
0*
0:
#37000000
1!
1*
0.
b1110 4
1:
bx001 ;
b1100 ?
#37200000
0!
0*
0:
#37400000
1!
1*
0.
b1111 4
1:
bx001 ;
b1101 ?
#37600000
0!
0*
0:
#37800000
1!
1*
0.
b10000 4
1:
bx001 ;
b1110 ?
#38000000
0!
0*
0:
#38200000
1!
1*
0.
b10001 4
1:
bx001 ;
b1111 ?
#38400000
0!
0*
0:
#38600000
1!
1*
0.
b10010 4
1:
bx001 ;
b10000 ?
#38800000
0!
0*
0:
#39000000
1!
1*
0.
b10011 4
1:
bx001 ;
b10001 ?
#39200000
0!
0*
0:
#39400000
1!
1*
0.
b10100 4
1:
bx001 ;
b10010 ?
#39600000
0!
0*
0:
#39800000
1!
1*
0.
b10101 4
1:
bx001 ;
b10011 ?
#40000000
0!
0*
0:
#40200000
1!
1*
0.
b10110 4
1:
bx001 ;
b10100 ?
#40400000
0!
0*
0:
#40600000
1!
1*
0.
b10111 4
1:
bx001 ;
b10101 ?
#40800000
0!
0*
0:
#41000000
1!
1*
0.
b11000 4
1:
bx001 ;
b10110 ?
#41200000
0!
0*
0:
#41400000
1!
1*
0.
b11001 4
1:
bx001 ;
b10111 ?
#41600000
0!
0*
0:
#41800000
1!
1*
0.
b0 4
b11 5
1:
bx001 ;
b11000 ?
#42000000
0!
0*
0:
#42200000
1!
1*
0.
b1 4
1:
bx001 ;
b11001 ?
#42400000
0!
0*
0:
#42600000
1!
1*
0.
b10 4
1:
b0 ?
b11 @
#42800000
0!
0*
0:
#43000000
1!
bx0001 )
1*
0.
b11 4
1:
bx0001 ;
b1 ?
#43200000
0!
0*
0:
#43400000
1!
1*
0.
b100 4
1:
bx0001 ;
b10 ?
#43600000
0!
0*
0:
#43800000
1!
1*
0.
b101 4
1:
bx0001 ;
b11 ?
#44000000
0!
0*
0:
#44200000
1!
1*
0.
b110 4
1:
bx0001 ;
b100 ?
#44400000
0!
0*
0:
#44600000
1!
1*
0.
b111 4
1:
bx0001 ;
b101 ?
#44800000
0!
0*
0:
#45000000
1!
1*
0.
b1000 4
1:
bx0001 ;
b110 ?
#45200000
0!
0*
0:
#45400000
1!
1*
0.
b1001 4
1:
bx0001 ;
b111 ?
#45600000
0!
0*
0:
#45800000
1!
1*
0.
b1010 4
1:
bx0001 ;
b1000 ?
#46000000
0!
0*
0:
#46200000
1!
1*
0.
b1011 4
1:
bx0001 ;
b1001 ?
#46400000
0!
0*
0:
#46600000
1!
1*
0.
b1100 4
1:
bx0001 ;
b1010 ?
#46800000
0!
0*
0:
#47000000
1!
1*
0.
b1101 4
1:
bx0001 ;
b1011 ?
#47200000
0!
0*
0:
#47400000
1!
1*
0.
b1110 4
1:
bx0001 ;
b1100 ?
#47600000
0!
0*
0:
#47800000
1!
1*
0.
b1111 4
1:
bx0001 ;
b1101 ?
#48000000
0!
0*
0:
#48200000
1!
1*
0.
b10000 4
1:
bx0001 ;
b1110 ?
#48400000
0!
0*
0:
#48600000
1!
1*
0.
b10001 4
1:
bx0001 ;
b1111 ?
#48800000
0!
0*
0:
#49000000
1!
1*
0.
b10010 4
1:
bx0001 ;
b10000 ?
#49200000
0!
0*
0:
#49400000
1!
1*
0.
b10011 4
1:
bx0001 ;
b10001 ?
#49600000
0!
0*
0:
#49800000
1!
1*
0.
b10100 4
1:
bx0001 ;
b10010 ?
#50000000
0!
0*
0:
#50200000
1!
1*
0.
b10101 4
1:
bx0001 ;
b10011 ?
#50400000
0!
0*
0:
#50600000
1!
1*
0.
b10110 4
1:
bx0001 ;
b10100 ?
